.VERSION
AUTHORS.rst
CONTRIBUTING.rst
HISTORY.rst
LICENSE
MANIFEST.in
Pipfile
Pipfile.lock
README.rst
dev-requirements.txt
requirements.txt
setup.cfg
setup.py
abelmokadem_awsapilib.egg-info/PKG-INFO
abelmokadem_awsapilib.egg-info/SOURCES.txt
abelmokadem_awsapilib.egg-info/dependency_links.txt
abelmokadem_awsapilib.egg-info/not-zip-safe
abelmokadem_awsapilib.egg-info/requires.txt
abelmokadem_awsapilib.egg-info/top_level.txt
awsapilib/.VERSION
awsapilib/AUTHORS.rst
awsapilib/CONTRIBUTING.rst
awsapilib/HISTORY.rst
awsapilib/LICENSE
awsapilib/Pipfile
awsapilib/Pipfile.lock
awsapilib/README.rst
awsapilib/USAGE_BILLING.rst
awsapilib/USAGE_CONTROL_TOWER.rst
awsapilib/USAGE_SSO.rst
awsapilib/__init__.py
awsapilib/_version.py
awsapilib/awsapilib.py
awsapilib/awsapilibexceptions.py
awsapilib/dev-requirements.txt
awsapilib/requirements.txt
awsapilib/authentication/__init__.py
awsapilib/authentication/authentication.py
awsapilib/authentication/authenticationexceptions.py
awsapilib/authentication/utils.py
awsapilib/billing/__init__.py
awsapilib/billing/billing.py
awsapilib/billing/billingexceptions.py
awsapilib/controltower/__init__.py
awsapilib/controltower/controltower.py
awsapilib/controltower/controltowerexceptions.py
awsapilib/controltower/resources/__init__.py
awsapilib/controltower/resources/configuration.py
awsapilib/controltower/resources/resources.py
awsapilib/sso/__init__.py
awsapilib/sso/sso.py
awsapilib/sso/ssoexceptions.py
awsapilib/sso/entities/__init__.py
awsapilib/sso/entities/entities.py
docs/Makefile
docs/authors.rst
docs/conf.py
docs/contributing.rst
docs/history.rst
docs/index.rst
docs/installation.rst
docs/readme.rst
docs/usage.rst