Metadata-Version: 2.1
Name: abelmokadem-awsapilib
Version: 0.2.2
Summary: A python library that exposes AWS services that are not covered by boto3, through the usage of undocumented APIs.
Home-page: https://github.com/schubergphilis/awsapilib
Author: Costas Tyfoxylos
Author-email: ctyfoxylos@schubergphilis.com
License: MIT
Keywords: awsapilib AWS api
Platform: UNKNOWN
Classifier: Development Status :: 4 - Beta
Classifier: Intended Audience :: Developers
Classifier: License :: OSI Approved :: MIT License
Classifier: Natural Language :: English
Classifier: Programming Language :: Python :: 3.7
License-File: LICENSE
License-File: AUTHORS.rst
